txxlz/__init__.py
txxlz/__main__.py
txxlz/ip.py
txxlz-1.1.0.dist-info/DESCRIPTION.rst
txxlz-1.1.0.dist-info/METADATA
txxlz-1.1.0.dist-info/RECORD
txxlz-1.1.0.dist-info/WHEEL
txxlz-1.1.0.dist-info/entry_points.txt
txxlz-1.1.0.dist-info/metadata.json
txxlz-1.1.0.dist-info/top_level.txt
