Metadata-Version: 2.0
Name: txxlz
Version: 1.1.0
Summary: Simple Small Python tools
Home-page: https://github.com/ignertic/txxlz
Author: Gishobert (SuperCode) Gwenzi
Author-email: ilovebugsincode@gmail.com
License: MIT
Platform: UNKNOWN
Classifier: Programming Language :: Python :: 3
Classifier: Operating System :: OS Independent
Requires-Dist: requests
